aws_cf/__init__.py
aws_cf/__main__.py
aws_cf/meta.py
aws_cf/commands/deploy.py
aws_cf/commands/destroy.py
aws_cf/commands/diff.py
aws_cf/commands/drift.py
aws_cf/commands/info.py
aws_cf/commands/init.py
aws_cf/commands/package.py
aws_cf/utils/__init__.py
aws_cf/utils/common.py
aws_cf/utils/config.py
aws_cf/utils/context.py
aws_cf/utils/logging.py
aws_cf-1.3.1.dist-info/licenses/LICENSE
aws_cf-1.3.1.dist-info/METADATA
aws_cf-1.3.1.dist-info/WHEEL
aws_cf-1.3.1.dist-info/entry_points.txt
aws_cf-1.3.1.dist-info/top_level.txt
aws_cf-1.3.1.dist-info/RECORD
