Metadata-Version: 2.4
Name: aws-cf
Version: 1.3.1
Summary: Simple way to deploy AWS stacks
Home-page: https://github.com/erikschmutz/aws-cf/
Author: Erik Rehn
Author-email: erik.rehn98@gmail.com
License: BSD 2-clause
License-File: LICENSE
Requires-Dist: pydantic
Requires-Dist: boto3
Requires-Dist: pyaml
Requires-Dist: requests
Dynamic: author
Dynamic: author-email
Dynamic: description
Dynamic: home-page
Dynamic: license
Dynamic: license-file
Dynamic: requires-dist
Dynamic: summary
